LICENCE
MANIFEST.in
README.rst
setup.cfg
setup.py
bambumain.egg-info/PKG-INFO
bambumain.egg-info/SOURCES.txt
bambumain.egg-info/dependency_links.txt
bambumain.egg-info/requires.txt
bambumain.egg-info/top_level.txt
main/__init__.py
main/admin.py
main/apps.py
main/decorators.py
main/models.py
main/tests.py
main/urls.py
main/views.py
main/migrations/__init__.py
main/templates/.DS_Store
main/templates/main/dashboard.html
main/templates/main/login.html
main/templates/main/painel.html
main/templates/main/userperfil.html
main/views/__init__.py
main/views/view_main.py